<?xml version="1.0" encoding="UTF-8"?>
<!--The Universal Instrumentation Code (UIC) by Peter Grimshaw of Zinfonia Holdings Pty Ltd (https://uic.btmi.au) is licensed under a Creative Commons Attribution 3.0 Unported License. http://creativecommons.org/licenses/by/3.0/deed.en_US-->
<result>
  <UIC>
    <GenusType>1.General</GenusType>
    <GenusID>1</GenusID>
    <GenusName>Scores</GenusName>
    <GenusNameDE>Partituren</GenusNameDE>
    <GenusNameFR>Partitions</GenusNameFR>
    <GenusNameIT>Partiture</GenusNameIT>
    <GenusNameES>Partituras</GenusNameES>
    <GenusNameJA>スコア</GenusNameJA>
    <GenusNameKO>악보</GenusNameKO>
    <GenusNamePL>Partytury</GenusNamePL>
    <GenusNamePT>Partituras</GenusNamePT>
    <GenusNameRU>Партитуры</GenusNameRU>
    <GenusNameZH>总谱</GenusNameZH>
    <GenusOrder>1</GenusOrder>
  </UIC>
  <UIC>
    <GenusType>1.General</GenusType>
    <GenusID>2</GenusID>
    <GenusName>Reduced Scores</GenusName>
    <GenusNameDE>Auszüge</GenusNameDE>
    <GenusNameFR>Partitions réduites </GenusNameFR>
    <GenusNameIT>Partiture ridotte</GenusNameIT>
    <GenusNameES>Partituras reducidas</GenusNameES>
    <GenusNameJA>抜粋、編集スコア</GenusNameJA>
    <GenusNameKO>축소악보</GenusNameKO>
    <GenusNamePL>Wyciągi i głosy dyrekcyjne</GenusNamePL>
    <GenusNamePT>Partituras reduzidas</GenusNamePT>
    <GenusNameRU>Отрывки</GenusNameRU>
    <GenusNameZH>简缩总谱</GenusNameZH>
    <GenusOrder>2</GenusOrder>
  </UIC>
  <UIC>
    <GenusType>1.General</GenusType>
    <GenusID>3</GenusID>
    <GenusIcon>Libretto</GenusIcon>
    <GenusName>Spoken Word and Action</GenusName>
    <GenusNameDE>Gesprochenes Wort und Handlung</GenusNameDE>
    <GenusNameFR>Texte parlé et action</GenusNameFR>
    <GenusNameIT>Testo recitato e azione</GenusNameIT>
    <GenusNameES>Texto hablado y acción</GenusNameES>
    <GenusNameJA>言葉とアクション</GenusNameJA>
    <GenusNameKO>시 낭송 그리고 움직임</GenusNameKO>
    <GenusNamePL>Partie mówione</GenusNamePL>
    <GenusNamePT>Texto falado e ação</GenusNamePT>
    <GenusNameRU>Декламация и действие</GenusNameRU>
    <GenusNameZH>台词与情节</GenusNameZH>
    <GenusOrder>3</GenusOrder>
  </UIC>
  <UIC>
    <GenusType>1.General</GenusType>
    <GenusID>4</GenusID>
    <GenusIcon>Ensemble</GenusIcon>
    <GenusName>Winds, Brass and Percussion</GenusName>
    <GenusNameDE>Holzbläser, Blechbläser und Percussion</GenusNameDE>
    <GenusNameFR>Instruments à vent, cuivres et percussions</GenusNameFR>
    <GenusNameIT>Legni ottoni e percussioni</GenusNameIT>
    <GenusNameES>Vientos, metales y percusión</GenusNameES>
    <GenusNameJA>菅打楽器</GenusNameJA>
    <GenusNameKO>목관악기, 금관악기 그리고 타악기</GenusNameKO>
    <GenusNamePL>Dęte i perkusja</GenusNamePL>
    <GenusNamePT>Instrumentos a sopro, metais e percussão</GenusNamePT>
    <GenusNameRU>Духовые и ударные</GenusNameRU>
    <GenusNameZH>木管，铜管和打击乐器</GenusNameZH>
    <GenusOrder>6</GenusOrder>
  </UIC>
  <UIC>
    <GenusType>1.General</GenusType>
    <GenusID>7</GenusID>
    <GenusName>Generic</GenusName>
    <GenusNameDE>Allgemein</GenusNameDE>
    <GenusNameFR>Générique</GenusNameFR>
    <GenusNameIT>Generico</GenusNameIT>
    <GenusNameES>Genérico</GenusNameES>
    <GenusNameJA>一般的な</GenusNameJA>
    <GenusNameKO>일반적인</GenusNameKO>
    <GenusNamePL>Ogólne</GenusNamePL>
    <GenusNamePT>Genérico</GenusNamePT>
    <GenusNameRU>Общее</GenusNameRU>
    <GenusNameZH>总体的</GenusNameZH>
    <GenusOrder>7</GenusOrder>
  </UIC>
  <UIC>
    <GenusType>1.General</GenusType>
    <GenusID>6</GenusID>
    <GenusIcon>Ensemble</GenusIcon>
    <GenusName>Groups</GenusName>
    <GenusNameDE>Gruppen</GenusNameDE>
    <GenusNameFR>Groupes</GenusNameFR>
    <GenusNameIT>Gruppi</GenusNameIT>
    <GenusNameES>Grupos</GenusNameES>
    <GenusNameJA>グループ</GenusNameJA>
    <GenusNameKO>그룹</GenusNameKO>
    <GenusNamePL>Zespoły</GenusNamePL>
    <GenusNamePT>Grupos</GenusNamePT>
    <GenusNameRU>Группы</GenusNameRU>
    <GenusNameZH>分组／各组</GenusNameZH>
    <GenusOrder>9</GenusOrder>
  </UIC>
  <UIC>
    <GenusType>1.General</GenusType>
    <GenusID>8</GenusID>
    <GenusName>Ethnic</GenusName>
    <GenusNameDE>Ethnisch</GenusNameDE>
    <GenusNameFR>Ethnique</GenusNameFR>
    <GenusNameIT>Etnico</GenusNameIT>
    <GenusNameES>Étnico</GenusNameES>
    <GenusNameJA>民族の</GenusNameJA>
    <GenusNameKO>민족</GenusNameKO>
    <GenusNamePL>Etniczne</GenusNamePL>
    <GenusNamePT>Étnico</GenusNamePT>
    <GenusNameRU>Этническое</GenusNameRU>
    <GenusNameZH>民族的</GenusNameZH>
    <GenusOrder>10</GenusOrder>
  </UIC>
  <UIC>
    <GenusType>1.General</GenusType>
    <GenusID>5</GenusID>
    <GenusName>Miscellaneous</GenusName>
    <GenusNameDE>Verschiedenes</GenusNameDE>
    <GenusNameFR>Divers</GenusNameFR>
    <GenusNameIT>Miscellanea</GenusNameIT>
    <GenusNameES>Mixto</GenusNameES>
    <GenusNameJA>様々な、多様な</GenusNameJA>
    <GenusNameKO>그밖에</GenusNameKO>
    <GenusNamePL>Różne</GenusNamePL>
    <GenusNamePT>Misto</GenusNamePT>
    <GenusNameRU>Разное</GenusNameRU>
    <GenusNameZH>各种不同的</GenusNameZH>
    <GenusOrder>13</GenusOrder>
  </UIC>
  <UIC>
    <GenusType>1.General</GenusType>
    <GenusID>9</GenusID>
    <GenusName>NOT USED</GenusName>
    <GenusNameDE>NOT USED</GenusNameDE>
    <GenusNameFR>NOT USED</GenusNameFR>
    <GenusNameIT>NON USATO</GenusNameIT>
    <GenusNameES>NO UTILIZADO</GenusNameES>
    <GenusNameJA>未使用</GenusNameJA>
    <GenusNameKO>사용안함</GenusNameKO>
    <GenusNamePL>NOT USED</GenusNamePL>
    <GenusNamePT>NÃO UTILIZADO</GenusNamePT>
    <GenusNameRU>НЕ ИСПОЛЬЗОВАЛОСЬ</GenusNameRU>
    <GenusNameZH>未使用过的</GenusNameZH>
    <GenusOrder>14</GenusOrder>
  </UIC>
  <UIC>
    <GenusType>2.Vocal</GenusType>
    <GenusID>1</GenusID>
    <GenusName>Vocal</GenusName>
    <GenusNameDE>Gesang</GenusNameDE>
    <GenusNameFR>Vocal</GenusNameFR>
    <GenusNameIT>Vocale</GenusNameIT>
    <GenusNameES>Vocal</GenusNameES>
    <GenusNameJA>声楽</GenusNameJA>
    <GenusNameKO>성악</GenusNameKO>
    <GenusNamePL>Głosy wokalne</GenusNamePL>
    <GenusNamePT>Vocal</GenusNamePT>
    <GenusNameRU>Вокал</GenusNameRU>
    <GenusNameZH>声乐</GenusNameZH>
    <GenusOrder>2</GenusOrder>
  </UIC>
  <UIC>
    <GenusType>2.Vocal</GenusType>
    <GenusID>2</GenusID>
    <GenusName>Vocal Parts</GenusName>
    <GenusNameDE>Gesang</GenusNameDE>
    <GenusNameFR>Parties vocales </GenusNameFR>
    <GenusNameIT>Parti vocali</GenusNameIT>
    <GenusNameES>Partes vocales</GenusNameES>
    <GenusNameJA>声部</GenusNameJA>
    <GenusNameKO>성악파트</GenusNameKO>
    <GenusNamePL>Głosy wokalne</GenusNamePL>
    <GenusNamePT>Partes vocais</GenusNamePT>
    <GenusNameRU>Партия вокала</GenusNameRU>
    <GenusNameZH>声乐部分</GenusNameZH>
    <GenusOrder>5</GenusOrder>
  </UIC>
  <UIC>
    <GenusType>2.Vocal</GenusType>
    <GenusID>4</GenusID>
    <GenusIcon>VocalScore</GenusIcon>
    <GenusName>Piano Vocal</GenusName>
    <GenusNameDE>Klavierauszug</GenusNameDE>
    <GenusNameFR>Piano chant</GenusNameFR>
    <GenusNameIT>Canto e piano</GenusNameIT>
    <GenusNameES>Canto y piano</GenusNameES>
    <GenusNameJA>ピアノと声楽</GenusNameJA>
    <GenusNameKO>피아노 편곡</GenusNameKO>
    <GenusNamePL>Wyciąg fortepianowy</GenusNamePL>
    <GenusNamePT>Canto e piano</GenusNamePT>
    <GenusNameRU>Фортепианная партия</GenusNameRU>
    <GenusNameZH>钢琴声部</GenusNameZH>
    <GenusOrder>6</GenusOrder>
  </UIC>
  <UIC>
    <GenusType>2.Vocal</GenusType>
    <GenusID>3</GenusID>
    <GenusIcon>Chorus</GenusIcon>
    <GenusName>Chorus Parts</GenusName>
    <GenusNameDE>Chorstimmen</GenusNameDE>
    <GenusNameFR>Parties de Chœur</GenusNameFR>
    <GenusNameIT>Parti coro</GenusNameIT>
    <GenusNameES>Partes del Coro</GenusNameES>
    <GenusNameJA>合唱声部</GenusNameJA>
    <GenusNameKO>합창파트</GenusNameKO>
    <GenusNamePL>Chór</GenusNamePL>
    <GenusNamePT>Partes de coro</GenusNamePT>
    <GenusNameRU>Партии хора</GenusNameRU>
    <GenusNameZH>合唱声部</GenusNameZH>
    <GenusOrder>9</GenusOrder>
  </UIC>
  <UIC>
    <GenusType>3.Wind</GenusType>
    <GenusID>11</GenusID>
    <GenusName>Wind</GenusName>
    <GenusNameDE>Holzbläser</GenusNameDE>
    <GenusNameFR>Instrument à vent</GenusNameFR>
    <GenusNameIT>Fiati</GenusNameIT>
    <GenusNameES>Viento</GenusNameES>
    <GenusNameJA>木管楽器</GenusNameJA>
    <GenusNameKO>목관</GenusNameKO>
    <GenusNamePL>Drzewo</GenusNamePL>
    <GenusNamePT>Sopro</GenusNamePT>
    <GenusNameRU>Деревянные духовые</GenusNameRU>
    <GenusNameZH>木管乐</GenusNameZH>
    <GenusOrder>1</GenusOrder>
  </UIC>
  <UIC>
    <GenusType>3.Wind</GenusType>
    <GenusID>1</GenusID>
    <GenusIcon>Flute</GenusIcon>
    <GenusName>Flutes</GenusName>
    <GenusNameDE>Flöten</GenusNameDE>
    <GenusNameFR>Flûtes</GenusNameFR>
    <GenusNameIT>Flauti</GenusNameIT>
    <GenusNameES>Flautas</GenusNameES>
    <GenusNameJA>フルート</GenusNameJA>
    <GenusNameKO>플룻</GenusNameKO>
    <GenusNamePL>Flety</GenusNamePL>
    <GenusNamePT>Flautas</GenusNamePT>
    <GenusNameRU>Флейты</GenusNameRU>
    <GenusNameZH>长笛</GenusNameZH>
    <GenusOrder>2</GenusOrder>
  </UIC>
  <UIC>
    <GenusType>3.Wind</GenusType>
    <GenusID>6</GenusID>
    <GenusIcon>Recorder</GenusIcon>
    <GenusName>Recorders</GenusName>
    <GenusNameDE>Blockflöten</GenusNameDE>
    <GenusNameFR>Flûtes à bec </GenusNameFR>
    <GenusNameIT>Flauti a becco</GenusNameIT>
    <GenusNameES>Flautas dulces</GenusNameES>
    <GenusNameJA>リコーダー</GenusNameJA>
    <GenusNameKO>리코더</GenusNameKO>
    <GenusNamePL>Flety proste</GenusNamePL>
    <GenusNamePT>Flautas doces</GenusNamePT>
    <GenusNameRU>Блокфлейты</GenusNameRU>
    <GenusNameZH>竖笛</GenusNameZH>
    <GenusOrder>9</GenusOrder>
  </UIC>
  <UIC>
    <GenusType>3.Wind</GenusType>
    <GenusID>2</GenusID>
    <GenusIcon>Oboe</GenusIcon>
    <GenusName>Oboes</GenusName>
    <GenusNameDE>Oboen</GenusNameDE>
    <GenusNameFR>Hautbois</GenusNameFR>
    <GenusNameIT>Oboi</GenusNameIT>
    <GenusNameES>Oboes</GenusNameES>
    <GenusNameJA>オーボエ</GenusNameJA>
    <GenusNameKO>오보에</GenusNameKO>
    <GenusNamePL>Oboje</GenusNamePL>
    <GenusNamePT>Oboés</GenusNamePT>
    <GenusNameRU>Гобои</GenusNameRU>
    <GenusNameZH>双簧管</GenusNameZH>
    <GenusOrder>11</GenusOrder>
  </UIC>
  <UIC>
    <GenusType>3.Wind</GenusType>
    <GenusID>13</GenusID>
    <GenusName>Crumhorns</GenusName>
    <GenusNameDE>Krummhörner</GenusNameDE>
    <GenusNameFR>Cromorne</GenusNameFR>
    <GenusNameIT>Cromorno</GenusNameIT>
    <GenusNameES>Cromornos</GenusNameES>
    <GenusNameJA>クルムホルン</GenusNameJA>
    <GenusNameKO>크럼호른</GenusNameKO>
    <GenusNamePL>Krummhorny</GenusNamePL>
    <GenusNamePT>Cromornos</GenusNamePT>
    <GenusNameRU>Крумхорны</GenusNameRU>
    <GenusNameZH>歪角号</GenusNameZH>
    <GenusOrder>12</GenusOrder>
  </UIC>
  <UIC>
    <GenusType>3.Wind</GenusType>
    <GenusID>8</GenusID>
    <GenusName>Sarrusophones</GenusName>
    <GenusNameDE>Sarrusophone</GenusNameDE>
    <GenusNameFR>Sarrussophones</GenusNameFR>
    <GenusNameIT>Sarrusofoni</GenusNameIT>
    <GenusNameES>Sarrusofones</GenusNameES>
    <GenusNameJA>サリュソホーン</GenusNameJA>
    <GenusNameKO>사뤼소폰</GenusNameKO>
    <GenusNamePL>Sarusofony</GenusNamePL>
    <GenusNamePT>Sarrusofones</GenusNamePT>
    <GenusNameRU>Саррюзофоны</GenusNameRU>
    <GenusNameZH>萨路号</GenusNameZH>
    <GenusOrder>18</GenusOrder>
  </UIC>
  <UIC>
    <GenusType>3.Wind</GenusType>
    <GenusID>3</GenusID>
    <GenusIcon>Clarinet</GenusIcon>
    <GenusName>Clarinets</GenusName>
    <GenusNameDE>Klarinetten</GenusNameDE>
    <GenusNameFR>Clarinettes </GenusNameFR>
    <GenusNameIT>Clarinetti</GenusNameIT>
    <GenusNameES>Clarinetes</GenusNameES>
    <GenusNameJA>クラリネット</GenusNameJA>
    <GenusNameKO>클라리넷</GenusNameKO>
    <GenusNamePL>Klarnety</GenusNamePL>
    <GenusNamePT>Clarinetes</GenusNamePT>
    <GenusNameRU>Кларнеты</GenusNameRU>
    <GenusNameZH>单簧管</GenusNameZH>
    <GenusOrder>20</GenusOrder>
  </UIC>
  <UIC>
    <GenusType>3.Wind</GenusType>
    <GenusID>5</GenusID>
    <GenusIcon>Saxophone</GenusIcon>
    <GenusName>Saxophones</GenusName>
    <GenusNameDE>Saxophone</GenusNameDE>
    <GenusNameFR>Saxophones</GenusNameFR>
    <GenusNameIT>Sassofoni</GenusNameIT>
    <GenusNameES>Saxofones</GenusNameES>
    <GenusNameJA>サクソフォーン</GenusNameJA>
    <GenusNameKO>섹소폰</GenusNameKO>
    <GenusNamePL>Saksofony</GenusNamePL>
    <GenusNamePT>Saxofones</GenusNamePT>
    <GenusNameRU>Саксофоны</GenusNameRU>
    <GenusNameZH>萨克斯风</GenusNameZH>
    <GenusOrder>21</GenusOrder>
  </UIC>
  <UIC>
    <GenusType>3.Wind</GenusType>
    <GenusID>4</GenusID>
    <GenusIcon>Bassoon</GenusIcon>
    <GenusName>Bassoons</GenusName>
    <GenusNameDE>Fagotte</GenusNameDE>
    <GenusNameFR>Bassons</GenusNameFR>
    <GenusNameIT>Fagotti</GenusNameIT>
    <GenusNameES>Fagots</GenusNameES>
    <GenusNameJA>ファゴット</GenusNameJA>
    <GenusNameKO>바순</GenusNameKO>
    <GenusNamePL>Fagoty</GenusNamePL>
    <GenusNamePT>Fagotes</GenusNamePT>
    <GenusNameRU>Фаготы</GenusNameRU>
    <GenusNameZH>巴松</GenusNameZH>
    <GenusOrder>23</GenusOrder>
  </UIC>
  <UIC>
    <GenusType>3.Wind</GenusType>
    <GenusID>14</GenusID>
    <GenusName>Ancient Wind</GenusName>
    <GenusNameDE>Antike Bläser</GenusNameDE>
    <GenusNameFR>Vent antique</GenusNameFR>
    <GenusNameIT>Antichi legni</GenusNameIT>
    <GenusNameES>Vientos antiguos</GenusNameES>
    <GenusNameJA>木管古楽器</GenusNameJA>
    <GenusNameKO>고대목관악기</GenusNameKO>
    <GenusNamePL>Ancient Wind</GenusNamePL>
    <GenusNamePT>Sopros antigos</GenusNamePT>
    <GenusNameRU>Старинные духовые</GenusNameRU>
    <GenusNameZH>古代吹管乐器</GenusNameZH>
    <GenusOrder>24</GenusOrder>
  </UIC>
  <UIC>
    <GenusType>3.Wind</GenusType>
    <GenusID>9</GenusID>
    <GenusName>Non-Western Flutes</GenusName>
    <GenusNameDE>Ethnische Flöten</GenusNameDE>
    <GenusNameFR>Flûtes ethniques</GenusNameFR>
    <GenusNameIT>Flauti etnici</GenusNameIT>
    <GenusNameES>Flautas étnicas</GenusNameES>
    <GenusNameJA>民族笛</GenusNameJA>
    <GenusNameKO>민족피리</GenusNameKO>
    <GenusNamePL>Etniczne flety</GenusNamePL>
    <GenusNamePT>Flautas étnicas</GenusNamePT>
    <GenusNameRU>Этнические флейты</GenusNameRU>
    <GenusNameZH>笛子</GenusNameZH>
    <GenusOrder>27</GenusOrder>
  </UIC>
  <UIC>
    <GenusType>3.Wind</GenusType>
    <GenusID>10</GenusID>
    <GenusName>Non-Western Reeds</GenusName>
    <GenusNameDE>Ethnische Rohrblattinstrumente</GenusNameDE>
    <GenusNameFR>Instruments à anche ethniques </GenusNameFR>
    <GenusNameIT>Ance etniche</GenusNameIT>
    <GenusNameES>Instrumentos de lengüeta étnicos</GenusNameES>
    <GenusNameJA>民族リード楽器</GenusNameJA>
    <GenusNameKO>민족 리드도 만들어진 악기</GenusNameKO>
    <GenusNamePL>Etniczne stroikowe</GenusNamePL>
    <GenusNamePT>Instrumentos de palheta étnicos</GenusNamePT>
    <GenusNameRU>Этнические язычковые инструменты</GenusNameRU>
    <GenusNameZH>民族吹管乐器</GenusNameZH>
    <GenusOrder>28</GenusOrder>
  </UIC>
  <UIC>
    <GenusType>3.Wind</GenusType>
    <GenusID>12</GenusID>
    <GenusIcon>Harmonica</GenusIcon>
    <GenusName>Melodicas</GenusName>
    <GenusNameDE>Melodicas</GenusNameDE>
    <GenusNameFR>Mélodicas</GenusNameFR>
    <GenusNameIT>Melodiche</GenusNameIT>
    <GenusNameES>Melódicas</GenusNameES>
    <GenusNameJA>メロディカ</GenusNameJA>
    <GenusNameKO>멜로디카</GenusNameKO>
    <GenusNamePL>Melodyki</GenusNamePL>
    <GenusNamePT>Escaletas</GenusNamePT>
    <GenusNameRU>Мелодики</GenusNameRU>
    <GenusNameZH>风琴</GenusNameZH>
    <GenusOrder>33</GenusOrder>
  </UIC>
  <UIC>
    <GenusType>3.Wind</GenusType>
    <GenusID>7</GenusID>
    <GenusIcon>Bagpipes</GenusIcon>
    <GenusName>Bagpipes</GenusName>
    <GenusNameDE>Dudelsäcke</GenusNameDE>
    <GenusNameFR>Cornemuses</GenusNameFR>
    <GenusNameIT>Cornamuse</GenusNameIT>
    <GenusNameES>Gaitas</GenusNameES>
    <GenusNameJA>バグパイプ</GenusNameJA>
    <GenusNameKO>백파이프</GenusNameKO>
    <GenusNamePL>Dudy</GenusNamePL>
    <GenusNamePT>Gaitas de fole</GenusNamePT>
    <GenusNameRU>Волынки</GenusNameRU>
    <GenusNameZH>风笛</GenusNameZH>
    <GenusOrder>35</GenusOrder>
  </UIC>
  <UIC>
    <GenusType>3.Wind</GenusType>
    <GenusID>15</GenusID>
    <GenusIcon>Generic</GenusIcon>
    <GenusName>Novelty</GenusName>
    <GenusNameDE>Ungewöhnliches</GenusNameDE>
    <GenusNameFR>Peu commun</GenusNameFR>
    <GenusNameIT>Insolito</GenusNameIT>
    <GenusNameES>Inusual</GenusNameES>
    <GenusNameJA>普通でない</GenusNameJA>
    <GenusNameKO>독특한</GenusNameKO>
    <GenusNamePL>Novelty</GenusNamePL>
    <GenusNamePT>Incomum</GenusNamePT>
    <GenusNameRU>Необычное</GenusNameRU>
    <GenusNameZH>不常见的</GenusNameZH>
    <GenusOrder>36</GenusOrder>
  </UIC>
  <UIC>
    <GenusType>4.Brass</GenusType>
    <GenusID>12</GenusID>
    <GenusName>Brass</GenusName>
    <GenusNameDE>Blechbläser</GenusNameDE>
    <GenusNameFR>Cuivres</GenusNameFR>
    <GenusNameIT>Ottoni</GenusNameIT>
    <GenusNameES>Metales</GenusNameES>
    <GenusNameJA>金管楽器</GenusNameJA>
    <GenusNameKO>금관악기</GenusNameKO>
    <GenusNamePL>Blacha</GenusNamePL>
    <GenusNamePT>Metais</GenusNamePT>
    <GenusNameRU>Медные духовые</GenusNameRU>
    <GenusNameZH>铜管乐器</GenusNameZH>
    <GenusOrder>1</GenusOrder>
  </UIC>
  <UIC>
    <GenusType>4.Brass</GenusType>
    <GenusID>1</GenusID>
    <GenusIcon>Horn</GenusIcon>
    <GenusName>Horns</GenusName>
    <GenusNameDE>Hörner</GenusNameDE>
    <GenusNameFR>Cors</GenusNameFR>
    <GenusNameIT>Corni</GenusNameIT>
    <GenusNameES>Trompas</GenusNameES>
    <GenusNameJA>ホルン</GenusNameJA>
    <GenusNameKO>호른</GenusNameKO>
    <GenusNamePL>Rogi</GenusNamePL>
    <GenusNamePT>Trompas</GenusNamePT>
    <GenusNameRU>Валторны</GenusNameRU>
    <GenusNameZH>号</GenusNameZH>
    <GenusOrder>2</GenusOrder>
  </UIC>
  <UIC>
    <GenusType>4.Brass</GenusType>
    <GenusID>2</GenusID>
    <GenusIcon>Trumpet</GenusIcon>
    <GenusName>Trumpets</GenusName>
    <GenusNameDE>Trompeten</GenusNameDE>
    <GenusNameFR>Trompettes</GenusNameFR>
    <GenusNameIT>Trombe</GenusNameIT>
    <GenusNameES>Trompetas</GenusNameES>
    <GenusNameJA>トランペット</GenusNameJA>
    <GenusNameKO>트럼펫</GenusNameKO>
    <GenusNamePL>Trąbki</GenusNamePL>
    <GenusNamePT>Trompetes</GenusNamePT>
    <GenusNameRU>Трубы</GenusNameRU>
    <GenusNameZH>小号</GenusNameZH>
    <GenusOrder>3</GenusOrder>
  </UIC>
  <UIC>
    <GenusType>4.Brass</GenusType>
    <GenusID>10</GenusID>
    <GenusIcon>Cornet</GenusIcon>
    <GenusName>Cornets</GenusName>
    <GenusNameDE>Kornett</GenusNameDE>
    <GenusNameFR>Cornets</GenusNameFR>
    <GenusNameIT>Cornette</GenusNameIT>
    <GenusNameES>Cornetas</GenusNameES>
    <GenusNameJA>コルネット</GenusNameJA>
    <GenusNameKO>코넷</GenusNameKO>
    <GenusNamePL>Kornety</GenusNamePL>
    <GenusNamePT>Cornetas</GenusNamePT>
    <GenusNameRU>Корнеты</GenusNameRU>
    <GenusNameZH>小号</GenusNameZH>
    <GenusOrder>4</GenusOrder>
  </UIC>
  <UIC>
    <GenusType>4.Brass</GenusType>
    <GenusID>8</GenusID>
    <GenusName>Bugles</GenusName>
    <GenusNameDE>Bügelhörner</GenusNameDE>
    <GenusNameFR>Clairons</GenusNameFR>
    <GenusNameIT>Cornette</GenusNameIT>
    <GenusNameES>Cornetas</GenusNameES>
    <GenusNameJA>ビューグル</GenusNameJA>
    <GenusNameKO>나팔</GenusNameKO>
    <GenusNamePL>Buglehorny</GenusNamePL>
    <GenusNamePT>Cornetas naturais</GenusNamePT>
    <GenusNameRU>Саксгорны</GenusNameRU>
    <GenusNameZH>萨克号</GenusNameZH>
    <GenusOrder>11</GenusOrder>
  </UIC>
  <UIC>
    <GenusType>4.Brass</GenusType>
    <GenusID>9</GenusID>
    <GenusName>Flugelhorns</GenusName>
    <GenusNameDE>Flügelhörner</GenusNameDE>
    <GenusNameFR>Bugles</GenusNameFR>
    <GenusNameIT>Flicorni</GenusNameIT>
    <GenusNameES>Fiscornos</GenusNameES>
    <GenusNameJA>フリューゲルホルン</GenusNameJA>
    <GenusNameKO>플루겔호른</GenusNameKO>
    <GenusNamePL>Flugelhorny</GenusNamePL>
    <GenusNamePT>Fliscornes</GenusNamePT>
    <GenusNameRU>Флюгельгорны</GenusNameRU>
    <GenusNameZH>小号</GenusNameZH>
    <GenusOrder>12</GenusOrder>
  </UIC>
  <UIC>
    <GenusType>4.Brass</GenusType>
    <GenusID>3</GenusID>
    <GenusIcon>Trombone</GenusIcon>
    <GenusName>Trombones</GenusName>
    <GenusNameDE>Posaunen</GenusNameDE>
    <GenusNameFR>Trombones</GenusNameFR>
    <GenusNameIT>Tromboni</GenusNameIT>
    <GenusNameES>Trombones</GenusNameES>
    <GenusNameJA>トロンボーン</GenusNameJA>
    <GenusNameKO>트럼본</GenusNameKO>
    <GenusNamePL>Puzony</GenusNamePL>
    <GenusNamePT>Trombones</GenusNamePT>
    <GenusNameRU>Тромбоны</GenusNameRU>
    <GenusNameZH>长号</GenusNameZH>
    <GenusOrder>13</GenusOrder>
  </UIC>
  <UIC>
    <GenusType>4.Brass</GenusType>
    <GenusID>5</GenusID>
    <GenusIcon>Euphonium</GenusIcon>
    <GenusName>Saxhorns</GenusName>
    <GenusNameDE>Bügelhorn</GenusNameDE>
    <GenusNameFR>Saxhorns</GenusNameFR>
    <GenusNameIT>Flicorno</GenusNameIT>
    <GenusNameES>Bombardinos</GenusNameES>
    <GenusNameJA>サクソルン</GenusNameJA>
    <GenusNameKO>색스혼</GenusNameKO>
    <GenusNamePL>Sakshorny</GenusNamePL>
    <GenusNamePT>Saxotrompa</GenusNamePT>
    <GenusNameRU>Саксгорны</GenusNameRU>
    <GenusNameZH>萨克号</GenusNameZH>
    <GenusOrder>17</GenusOrder>
  </UIC>
  <UIC>
    <GenusType>4.Brass</GenusType>
    <GenusID>6</GenusID>
    <GenusIcon>Euphonium</GenusIcon>
    <GenusName>Euphoniums</GenusName>
    <GenusNameDE>Euphonien</GenusNameDE>
    <GenusNameFR>Euphoniums</GenusNameFR>
    <GenusNameIT>Euphonium</GenusNameIT>
    <GenusNameES>Bombardinos</GenusNameES>
    <GenusNameJA>ユーフォニウム</GenusNameJA>
    <GenusNameKO>유포니움</GenusNameKO>
    <GenusNamePL>Euphonium</GenusNamePL>
    <GenusNamePT>Eufónio</GenusNamePT>
    <GenusNameRU>Эуфониум</GenusNameRU>
    <GenusNameZH>次中音号</GenusNameZH>
    <GenusOrder>19</GenusOrder>
  </UIC>
  <UIC>
    <GenusType>4.Brass</GenusType>
    <GenusID>11</GenusID>
    <GenusName>Wagner Tubas</GenusName>
    <GenusNameDE>Wagnertuben</GenusNameDE>
    <GenusNameFR>Tubas wagnériens </GenusNameFR>
    <GenusNameIT>Tube wagneriane</GenusNameIT>
    <GenusNameES>Tubas wagnerianas</GenusNameES>
    <GenusNameJA>ワーグナーテューバ</GenusNameJA>
    <GenusNameKO>바그너 튜바</GenusNameKO>
    <GenusNamePL>Tuby wagnerowskie</GenusNamePL>
    <GenusNamePT>Trompa wagneriana</GenusNamePT>
    <GenusNameRU>Вагнеровские тубы</GenusNameRU>
    <GenusNameZH>瓦格纳大号</GenusNameZH>
    <GenusOrder>20</GenusOrder>
  </UIC>
  <UIC>
    <GenusType>4.Brass</GenusType>
    <GenusID>4</GenusID>
    <GenusIcon>Tuba</GenusIcon>
    <GenusName>Tubas and Basses</GenusName>
    <GenusNameDE>Tuben/Basstuben</GenusNameDE>
    <GenusNameFR>Tubas et Tubas Basses</GenusNameFR>
    <GenusNameIT>Tube e Bassotube</GenusNameIT>
    <GenusNameES>Tubas y bajos</GenusNameES>
    <GenusNameJA>テューバとバステューバ</GenusNameJA>
    <GenusNameKO>튜바 그리고 베이스</GenusNameKO>
    <GenusNamePL>Tuby</GenusNamePL>
    <GenusNamePT>Tubas e Baixos</GenusNamePT>
    <GenusNameRU>Тубы и Басовые тубы</GenusNameRU>
    <GenusNameZH>大号和低音号</GenusNameZH>
    <GenusOrder>21</GenusOrder>
  </UIC>
  <UIC>
    <GenusType>4.Brass</GenusType>
    <GenusID>13</GenusID>
    <GenusName>Ancient Brass</GenusName>
    <GenusNameDE>Ancient Brass</GenusNameDE>
    <GenusNameFR>Cuivres anciens</GenusNameFR>
    <GenusNameIT>Ottoni antichi</GenusNameIT>
    <GenusNameES>Metales antiguos</GenusNameES>
    <GenusNameJA>金管古楽器</GenusNameJA>
    <GenusNameKO>고대금관악기</GenusNameKO>
    <GenusNamePL>Starożytne blaszane</GenusNamePL>
    <GenusNamePT>Metais antigos</GenusNamePT>
    <GenusNameRU>Древние медные духовые</GenusNameRU>
    <GenusNameZH>古代吹管乐器</GenusNameZH>
    <GenusOrder>22</GenusOrder>
  </UIC>
  <UIC>
    <GenusType>4.Brass</GenusType>
    <GenusID>7</GenusID>
    <GenusName>Non-metal</GenusName>
    <GenusNameDE>Nichtmetallisch</GenusNameDE>
    <GenusNameFR>Non métallique</GenusNameFR>
    <GenusNameIT>Non metallico</GenusNameIT>
    <GenusNameES>No metálico</GenusNameES>
    <GenusNameJA>メタルでない</GenusNameJA>
    <GenusNameKO>비금속</GenusNameKO>
    <GenusNamePL>Inne dęte</GenusNamePL>
    <GenusNamePT>Não metálico</GenusNamePT>
    <GenusNameRU>Неметаллические</GenusNameRU>
    <GenusNameZH>不带金属的</GenusNameZH>
    <GenusOrder>27</GenusOrder>
  </UIC>
  <UIC>
    <GenusType>5.Other</GenusType>
    <GenusID>1</GenusID>
    <GenusIcon>Percussion</GenusIcon>
    <GenusName>Timpani</GenusName>
    <GenusNameDE>Pauken</GenusNameDE>
    <GenusNameFR>Timbales </GenusNameFR>
    <GenusNameIT>Timpani</GenusNameIT>
    <GenusNameES>Timbales</GenusNameES>
    <GenusNameJA>ティンパニー</GenusNameJA>
    <GenusNameKO>팀파니</GenusNameKO>
    <GenusNamePL>Kotły</GenusNamePL>
    <GenusNamePT>Tímpanos</GenusNamePT>
    <GenusNameRU>Литавры</GenusNameRU>
    <GenusNameZH>定音鼓</GenusNameZH>
    <GenusOrder>1</GenusOrder>
  </UIC>
  <UIC>
    <GenusType>5.Other</GenusType>
    <GenusID>2</GenusID>
    <GenusIcon>Percussion</GenusIcon>
    <GenusName>Percussion</GenusName>
    <GenusNameDE>Schlagzeug</GenusNameDE>
    <GenusNameFR>Percussions</GenusNameFR>
    <GenusNameIT>Percussioni</GenusNameIT>
    <GenusNameES>Percusión</GenusNameES>
    <GenusNameJA>パーカッション</GenusNameJA>
    <GenusNameKO>타악기</GenusNameKO>
    <GenusNamePL>Perkusja</GenusNamePL>
    <GenusNamePT>Percussão</GenusNamePT>
    <GenusNameRU>Ударные инструменты</GenusNameRU>
    <GenusNameZH>打击乐</GenusNameZH>
    <GenusOrder>2</GenusOrder>
  </UIC>
  <UIC>
    <GenusType>5.Other</GenusType>
    <GenusID>22</GenusID>
    <GenusName>Ancient</GenusName>
    <GenusNameDE>alt</GenusNameDE>
    <GenusNameFR>Antique</GenusNameFR>
    <GenusNameIT>Antico</GenusNameIT>
    <GenusNameES>Antiguo</GenusNameES>
    <GenusNameJA>古い</GenusNameJA>
    <GenusNameKO>고대</GenusNameKO>
    <GenusNamePL>Ancient</GenusNamePL>
    <GenusNamePT>Antigo</GenusNamePT>
    <GenusNameRU>Старинное</GenusNameRU>
    <GenusNameZH>古老的</GenusNameZH>
    <GenusOrder>3</GenusOrder>
  </UIC>
  <UIC>
    <GenusType>5.Other</GenusType>
    <GenusID>18</GenusID>
    <GenusName>Non-Western Percussion</GenusName>
    <GenusNameDE>Ethnische Percussion</GenusNameDE>
    <GenusNameFR>Percussions ethniques </GenusNameFR>
    <GenusNameIT>Percussioni etniche</GenusNameIT>
    <GenusNameES>Percusión étnica</GenusNameES>
    <GenusNameJA>民族打楽器</GenusNameJA>
    <GenusNameKO>북</GenusNameKO>
    <GenusNamePL>Etniczna perkusja</GenusNamePL>
    <GenusNamePT>Percussão antiga</GenusNamePT>
    <GenusNameRU>Этнические ударные</GenusNameRU>
    <GenusNameZH>民族打击乐器</GenusNameZH>
    <GenusOrder>4</GenusOrder>
  </UIC>
  <UIC>
    <GenusType>5.Other</GenusType>
    <GenusID>19</GenusID>
    <GenusName>Non-Western Plucked</GenusName>
    <GenusNameDE>Ethnische Zupfinstrumente</GenusNameDE>
    <GenusNameFR>Instruments ethniques à cordes pincées</GenusNameFR>
    <GenusNameIT>Strumenti etnici a pizzico</GenusNameIT>
    <GenusNameES>Instrumentos étnicos de cuerda pulsada</GenusNameES>
    <GenusNameJA>民族撥弦楽器</GenusNameJA>
    <GenusNameKO>고대 현악기</GenusNameKO>
    <GenusNamePL>Etniczne szarpane</GenusNamePL>
    <GenusNamePT>Instrumentos de cordas beliscadas étnicos</GenusNamePT>
    <GenusNameRU>Этнические щипковые инструменты</GenusNameRU>
    <GenusNameZH>民族弹拨乐器</GenusNameZH>
    <GenusOrder>7</GenusOrder>
  </UIC>
  <UIC>
    <GenusType>5.Other</GenusType>
    <GenusID>17</GenusID>
    <GenusName>Other</GenusName>
    <GenusNameDE>Andere</GenusNameDE>
    <GenusNameFR>Autre</GenusNameFR>
    <GenusNameIT>Altro</GenusNameIT>
    <GenusNameES>Otro</GenusNameES>
    <GenusNameJA>その他</GenusNameJA>
    <GenusNameKO>그밖에</GenusNameKO>
    <GenusNamePL>Inne</GenusNamePL>
    <GenusNamePT>Outro</GenusNamePT>
    <GenusNameRU>Другое</GenusNameRU>
    <GenusNameZH>其它</GenusNameZH>
    <GenusOrder>10</GenusOrder>
  </UIC>
  <UIC>
    <GenusType>5.Other</GenusType>
    <GenusID>14</GenusID>
    <GenusName>Effects</GenusName>
    <GenusNameDE>Effekte</GenusNameDE>
    <GenusNameFR>Effets</GenusNameFR>
    <GenusNameIT>Effetti</GenusNameIT>
    <GenusNameES>Efectos</GenusNameES>
    <GenusNameJA>効果</GenusNameJA>
    <GenusNameKO>효과</GenusNameKO>
    <GenusNamePL>Efekty</GenusNamePL>
    <GenusNamePT>Efeitos</GenusNamePT>
    <GenusNameRU>Эффекты</GenusNameRU>
    <GenusNameZH>效果</GenusNameZH>
    <GenusOrder>12</GenusOrder>
  </UIC>
  <UIC>
    <GenusType>5.Other</GenusType>
    <GenusID>16</GenusID>
    <GenusName>Electronics</GenusName>
    <GenusNameDE>Electronics</GenusNameDE>
    <GenusNameFR>Electronique</GenusNameFR>
    <GenusNameIT>Elettronica</GenusNameIT>
    <GenusNameES>Electrónica</GenusNameES>
    <GenusNameJA>エレクトロニクス</GenusNameJA>
    <GenusNameKO>전자</GenusNameKO>
    <GenusNamePL>Elektronika</GenusNamePL>
    <GenusNamePT>Eletrónicos</GenusNamePT>
    <GenusNameRU>Электроника</GenusNameRU>
    <GenusNameZH>电子产品</GenusNameZH>
    <GenusOrder>13</GenusOrder>
  </UIC>
  <UIC>
    <GenusType>5.Other</GenusType>
    <GenusID>13</GenusID>
    <GenusName>Toys</GenusName>
    <GenusNameDE>Spielzeug</GenusNameDE>
    <GenusNameFR>Jouets</GenusNameFR>
    <GenusNameIT>Giocattoli</GenusNameIT>
    <GenusNameES>Juguetes</GenusNameES>
    <GenusNameJA>おもちゃ、玩具</GenusNameJA>
    <GenusNameKO>장난감</GenusNameKO>
    <GenusNamePL>Zabawki</GenusNamePL>
    <GenusNamePT>Brinquedos</GenusNamePT>
    <GenusNameRU>Игрушки</GenusNameRU>
    <GenusNameZH>玩具</GenusNameZH>
    <GenusOrder>15</GenusOrder>
  </UIC>
  <UIC>
    <GenusType>5.Other</GenusType>
    <GenusID>3</GenusID>
    <GenusIcon>Piano</GenusIcon>
    <GenusName>Keyboard</GenusName>
    <GenusNameDE>Tasteninstrumente</GenusNameDE>
    <GenusNameFR>Clavier</GenusNameFR>
    <GenusNameIT>Tastiera</GenusNameIT>
    <GenusNameES>Teclado</GenusNameES>
    <GenusNameJA>鍵盤楽器</GenusNameJA>
    <GenusNameKO>건반</GenusNameKO>
    <GenusNamePL>Klawiszowe</GenusNamePL>
    <GenusNamePT>Teclado</GenusNamePT>
    <GenusNameRU>Клавишные</GenusNameRU>
    <GenusNameZH>键盘乐器</GenusNameZH>
    <GenusOrder>17</GenusOrder>
  </UIC>
  <UIC>
    <GenusType>5.Other</GenusType>
    <GenusID>10</GenusID>
    <GenusIcon>Lute</GenusIcon>
    <GenusName>Lutes</GenusName>
    <GenusNameDE>Lauten</GenusNameDE>
    <GenusNameFR>Luths</GenusNameFR>
    <GenusNameIT>Liuti</GenusNameIT>
    <GenusNameES>Laúdes</GenusNameES>
    <GenusNameJA>リュート</GenusNameJA>
    <GenusNameKO>류트</GenusNameKO>
    <GenusNamePL>Lutnie</GenusNamePL>
    <GenusNamePT>Alaúdes</GenusNamePT>
    <GenusNameRU>Лютни</GenusNameRU>
    <GenusNameZH>琵琶</GenusNameZH>
    <GenusOrder>18</GenusOrder>
  </UIC>
  <UIC>
    <GenusType>5.Other</GenusType>
    <GenusID>9</GenusID>
    <GenusIcon>Guitar</GenusIcon>
    <GenusName>Guitars</GenusName>
    <GenusNameDE>Gitarren</GenusNameDE>
    <GenusNameFR>Guitares</GenusNameFR>
    <GenusNameIT>Chitarre</GenusNameIT>
    <GenusNameES>Guitarras</GenusNameES>
    <GenusNameJA>ギター</GenusNameJA>
    <GenusNameKO>기타</GenusNameKO>
    <GenusNamePL>Gitary</GenusNamePL>
    <GenusNamePT>Guitarras</GenusNamePT>
    <GenusNameRU>Гитары</GenusNameRU>
    <GenusNameZH>吉他</GenusNameZH>
    <GenusOrder>20</GenusOrder>
  </UIC>
  <UIC>
    <GenusType>5.Other</GenusType>
    <GenusID>7</GenusID>
    <GenusIcon>Banjo</GenusIcon>
    <GenusName>Banjos</GenusName>
    <GenusNameDE>Banjos</GenusNameDE>
    <GenusNameFR>Banjos</GenusNameFR>
    <GenusNameIT>Banjo</GenusNameIT>
    <GenusNameES>Banjos</GenusNameES>
    <GenusNameJA>バンジョー</GenusNameJA>
    <GenusNameKO>밴조</GenusNameKO>
    <GenusNamePL>Banjo</GenusNamePL>
    <GenusNamePT>Banjos</GenusNamePT>
    <GenusNameRU>Банджо</GenusNameRU>
    <GenusNameZH>班卓琴</GenusNameZH>
    <GenusOrder>22</GenusOrder>
  </UIC>
  <UIC>
    <GenusType>5.Other</GenusType>
    <GenusID>21</GenusID>
    <GenusName>Dulcimers</GenusName>
    <GenusNameDE>Dulcimer</GenusNameDE>
    <GenusNameFR>Dulcimers</GenusNameFR>
    <GenusNameIT>Dulcimer</GenusNameIT>
    <GenusNameES>Dulcémeles</GenusNameES>
    <GenusNameJA>ダルシマー、ツィンバロン</GenusNameJA>
    <GenusNameKO>덜시머</GenusNameKO>
    <GenusNamePL>Cymbały</GenusNamePL>
    <GenusNamePT>Dulcimers</GenusNamePT>
    <GenusNameRU>Дульцимеры</GenusNameRU>
    <GenusNameZH>杜其莫琴</GenusNameZH>
    <GenusOrder>23</GenusOrder>
  </UIC>
  <UIC>
    <GenusType>5.Other</GenusType>
    <GenusID>8</GenusID>
    <GenusName>Balalaikas</GenusName>
    <GenusNameDE>Balalaikas</GenusNameDE>
    <GenusNameFR>Balalaikas</GenusNameFR>
    <GenusNameIT>Balalaika</GenusNameIT>
    <GenusNameES>Balalaicas</GenusNameES>
    <GenusNameJA>バラライカ</GenusNameJA>
    <GenusNameKO>발랄라이카</GenusNameKO>
    <GenusNamePL>Bałałajki</GenusNamePL>
    <GenusNamePT>Balalaicas</GenusNamePT>
    <GenusNameRU>Балалайки</GenusNameRU>
    <GenusNameZH>巴拉莱卡琴</GenusNameZH>
    <GenusOrder>25</GenusOrder>
  </UIC>
  <UIC>
    <GenusType>5.Other</GenusType>
    <GenusID>4</GenusID>
    <GenusIcon>Harp</GenusIcon>
    <GenusName>Harp</GenusName>
    <GenusNameDE>Harfen</GenusNameDE>
    <GenusNameFR>Harpe</GenusNameFR>
    <GenusNameIT>Arpa</GenusNameIT>
    <GenusNameES>Arpa</GenusNameES>
    <GenusNameJA>ハープ</GenusNameJA>
    <GenusNameKO>하프</GenusNameKO>
    <GenusNamePL>Harfa</GenusNamePL>
    <GenusNamePT>Arpa</GenusNamePT>
    <GenusNameRU>Арфы</GenusNameRU>
    <GenusNameZH>竖琴</GenusNameZH>
    <GenusOrder>30</GenusOrder>
  </UIC>
  <UIC>
    <GenusType>5.Other</GenusType>
    <GenusID>5</GenusID>
    <GenusIcon>Accordion</GenusIcon>
    <GenusName>Accordions and Concertinas</GenusName>
    <GenusNameDE>Akkordeons und Concertinas</GenusNameDE>
    <GenusNameFR>Accordéons et concertinas</GenusNameFR>
    <GenusNameIT>Fisarmoniche e concertine</GenusNameIT>
    <GenusNameES>Acordeones y concertinas</GenusNameES>
    <GenusNameJA>アコーディオンとコンチェルティーナ</GenusNameJA>
    <GenusNameKO>아코디언 그리고 콘서티나</GenusNameKO>
    <GenusNamePL>Akordeony</GenusNamePL>
    <GenusNamePT>Acordeões e concertinas</GenusNamePT>
    <GenusNameRU>Аккордеоны и концертины</GenusNameRU>
    <GenusNameZH>手风琴</GenusNameZH>
    <GenusOrder>31</GenusOrder>
  </UIC>
  <UIC>
    <GenusType>5.Other</GenusType>
    <GenusID>15</GenusID>
    <GenusIcon>Harmonica</GenusIcon>
    <GenusName>Harmonicas</GenusName>
    <GenusNameDE>Harmonikas</GenusNameDE>
    <GenusNameFR>Harmonicas</GenusNameFR>
    <GenusNameIT>Armoniche</GenusNameIT>
    <GenusNameES>Armónicas</GenusNameES>
    <GenusNameJA>ハーモニカ</GenusNameJA>
    <GenusNameKO>하모니카</GenusNameKO>
    <GenusNamePL>Harmonijka ustna</GenusNamePL>
    <GenusNamePT>Harmónicas</GenusNamePT>
    <GenusNameRU>Губная гармоника</GenusNameRU>
    <GenusNameZH>口琴</GenusNameZH>
    <GenusOrder>32</GenusOrder>
  </UIC>
  <UIC>
    <GenusType>5.Other</GenusType>
    <GenusID>12</GenusID>
    <GenusName>Glass</GenusName>
    <GenusNameDE>Glas</GenusNameDE>
    <GenusNameFR>verre</GenusNameFR>
    <GenusNameIT>Bicchiere</GenusNameIT>
    <GenusNameES>Cristal</GenusNameES>
    <GenusNameJA>ガラス</GenusNameJA>
    <GenusNameKO>유리</GenusNameKO>
    <GenusNamePL>Szklane</GenusNamePL>
    <GenusNamePT>Vidro</GenusNamePT>
    <GenusNameRU>Стекло</GenusNameRU>
    <GenusNameZH>玻璃</GenusNameZH>
    <GenusOrder>36</GenusOrder>
  </UIC>
  <UIC>
    <GenusType>5.Other</GenusType>
    <GenusID>20</GenusID>
    <GenusName>Hurdy Gurdy</GenusName>
    <GenusNameDE>Drehleier</GenusNameDE>
    <GenusNameFR>Vielle à roue</GenusNameFR>
    <GenusNameIT>Ghironda</GenusNameIT>
    <GenusNameES>Zanfona</GenusNameES>
    <GenusNameJA>ハーディ・ガーディ</GenusNameJA>
    <GenusNameKO>허디 거디</GenusNameKO>
    <GenusNamePL>Lira korbowa</GenusNamePL>
    <GenusNamePT>Sanfona</GenusNamePT>
    <GenusNameRU>Колёсная лира</GenusNameRU>
    <GenusNameZH>手摇风琴</GenusNameZH>
    <GenusOrder>38</GenusOrder>
  </UIC>
  <UIC>
    <GenusType>5.Other</GenusType>
    <GenusID>23</GenusID>
    <GenusName>Other Sounds</GenusName>
    <GenusNameDE>Sonstige Klänge/Geräusche</GenusNameDE>
    <GenusNameFR>Autres sons</GenusNameFR>
    <GenusNameIT>Altri suoni</GenusNameIT>
    <GenusNameES>Otros sonidos</GenusNameES>
    <GenusNameJA>その他の音</GenusNameJA>
    <GenusNameKO>다른 소리들</GenusNameKO>
    <GenusNamePL>Inne sygnały dźwiękowe</GenusNamePL>
    <GenusNamePT>Outros sons</GenusNamePT>
    <GenusNameRU>Другие звуки</GenusNameRU>
    <GenusNameZH>其它的声音</GenusNameZH>
    <GenusOrder>39</GenusOrder>
  </UIC>
  <UIC>
    <GenusType>5.Other</GenusType>
    <GenusID>6</GenusID>
    <GenusIcon>Audio</GenusIcon>
    <GenusName>Recorded Sound and Vision</GenusName>
    <GenusNameDE>Ton- und Bildaufnahmen</GenusNameDE>
    <GenusNameFR>Son enregistré et vidéo</GenusNameFR>
    <GenusNameIT>Suoni registrati e video</GenusNameIT>
    <GenusNameES>Sonido y vídeo grabado</GenusNameES>
    <GenusNameJA>録音と映像</GenusNameJA>
    <GenusNameKO>소리 그리고 영상</GenusNameKO>
    <GenusNamePL>Nagrania</GenusNamePL>
    <GenusNamePT>Som e vídeo gravado</GenusNamePT>
    <GenusNameRU>Аудио- и видеозаписи</GenusNameRU>
    <GenusNameZH>录音和录像</GenusNameZH>
    <GenusOrder>45</GenusOrder>
  </UIC>
  <UIC>
    <GenusType>5.Other</GenusType>
    <GenusID>11</GenusID>
    <GenusName>Zithers</GenusName>
    <GenusNameDE>Zithern</GenusNameDE>
    <GenusNameFR>Cithares </GenusNameFR>
    <GenusNameIT>Cetra</GenusNameIT>
    <GenusNameES>Cítaras</GenusNameES>
    <GenusNameJA>ツィター</GenusNameJA>
    <GenusNameKO>치터</GenusNameKO>
    <GenusNamePL>Cytry</GenusNamePL>
    <GenusNamePT>Cítaras</GenusNamePT>
    <GenusNameRU>Цитра</GenusNameRU>
    <GenusNameZH>箏</GenusNameZH>
    <GenusOrder>46</GenusOrder>
  </UIC>
  <UIC>
    <GenusType>5.Other</GenusType>
    <GenusID>24</GenusID>
    <GenusName>Not Used</GenusName>
    <GenusNameDE>Schlüsselfidel</GenusNameDE>
    <GenusNameFR>Nyckelharpa</GenusNameFR>
    <GenusNameIT>Nyckelharpa</GenusNameIT>
    <GenusNameES>Nyckelharpa</GenusNameES>
    <GenusNameJA>Nyckelharpa</GenusNameJA>
    <GenusNameKO>Nyckelharpa</GenusNameKO>
    <GenusNamePL>Nyckelharpa</GenusNamePL>
    <GenusNamePT>Nyckelharpa</GenusNamePT>
    <GenusNameRU>Никельхарпа</GenusNameRU>
    <GenusNameZH>Nyckelharpa</GenusNameZH>
    <GenusOrder>47</GenusOrder>
  </UIC>
  <UIC>
    <GenusType>6.Strings</GenusType>
    <GenusID>7</GenusID>
    <GenusName>Strings</GenusName>
    <GenusNameDE>Streicher</GenusNameDE>
    <GenusNameFR>Cordes</GenusNameFR>
    <GenusNameIT>Archi</GenusNameIT>
    <GenusNameES>Cuerdas</GenusNameES>
    <GenusNameJA>弦楽器</GenusNameJA>
    <GenusNameKO>현악기</GenusNameKO>
    <GenusNamePL>Smyczki</GenusNamePL>
    <GenusNamePT>Cordas</GenusNamePT>
    <GenusNameRU>Струнные</GenusNameRU>
    <GenusNameZH>弦乐器</GenusNameZH>
    <GenusOrder>1</GenusOrder>
  </UIC>
  <UIC>
    <GenusType>6.Strings</GenusType>
    <GenusID>1</GenusID>
    <GenusIcon>Violin</GenusIcon>
    <GenusName>Violins</GenusName>
    <GenusNameDE>Violinen</GenusNameDE>
    <GenusNameFR>Violons</GenusNameFR>
    <GenusNameIT>Violini</GenusNameIT>
    <GenusNameES>Violines</GenusNameES>
    <GenusNameJA>ヴァイオリン</GenusNameJA>
    <GenusNameKO>바이올린</GenusNameKO>
    <GenusNamePL>Skrzypce</GenusNamePL>
    <GenusNamePT>Violinos</GenusNamePT>
    <GenusNameRU>Скрипки</GenusNameRU>
    <GenusNameZH>小提琴</GenusNameZH>
    <GenusOrder>2</GenusOrder>
  </UIC>
  <UIC>
    <GenusType>6.Strings</GenusType>
    <GenusID>2</GenusID>
    <GenusIcon>Viola</GenusIcon>
    <GenusName>Violas</GenusName>
    <GenusNameDE>Bratschen</GenusNameDE>
    <GenusNameFR>Violes</GenusNameFR>
    <GenusNameIT>Viole</GenusNameIT>
    <GenusNameES>Violas</GenusNameES>
    <GenusNameJA>ヴィオラ</GenusNameJA>
    <GenusNameKO>비올라</GenusNameKO>
    <GenusNamePL>Altówki</GenusNamePL>
    <GenusNamePT>Violas</GenusNamePT>
    <GenusNameRU>Альты</GenusNameRU>
    <GenusNameZH>中提琴</GenusNameZH>
    <GenusOrder>5</GenusOrder>
  </UIC>
  <UIC>
    <GenusType>6.Strings</GenusType>
    <GenusID>3</GenusID>
    <GenusIcon>Cello</GenusIcon>
    <GenusName>Cellos</GenusName>
    <GenusNameDE>Celli</GenusNameDE>
    <GenusNameFR>Violoncelles</GenusNameFR>
    <GenusNameIT>Violoncelli</GenusNameIT>
    <GenusNameES>Violonchelos</GenusNameES>
    <GenusNameJA>チェロ</GenusNameJA>
    <GenusNameKO>첼로</GenusNameKO>
    <GenusNamePL>Wiolonczele</GenusNamePL>
    <GenusNamePT>Violoncelos</GenusNamePT>
    <GenusNameRU>Виолончели</GenusNameRU>
    <GenusNameZH>大提琴</GenusNameZH>
    <GenusOrder>6</GenusOrder>
  </UIC>
  <UIC>
    <GenusType>6.Strings</GenusType>
    <GenusID>4</GenusID>
    <GenusIcon>DoubleBass</GenusIcon>
    <GenusName>Double Bass</GenusName>
    <GenusNameDE>Kontrabässe</GenusNameDE>
    <GenusNameFR>Contrebasse</GenusNameFR>
    <GenusNameIT>Contrabbasso</GenusNameIT>
    <GenusNameES>Contrabajo</GenusNameES>
    <GenusNameJA>コントラバス</GenusNameJA>
    <GenusNameKO>콘트라 베이스</GenusNameKO>
    <GenusNamePL>Kontrabasy</GenusNamePL>
    <GenusNamePT>Contrabaixo</GenusNamePT>
    <GenusNameRU>Контрабасы</GenusNameRU>
    <GenusNameZH>低音提琴</GenusNameZH>
    <GenusOrder>7</GenusOrder>
  </UIC>
  <UIC>
    <GenusType>6.Strings</GenusType>
    <GenusID>9</GenusID>
    <GenusIcon>DoubleBass</GenusIcon>
    <GenusName>Basso</GenusName>
    <GenusNameDE>Bass</GenusNameDE>
    <GenusNameFR>Basse</GenusNameFR>
    <GenusNameIT>Basso</GenusNameIT>
    <GenusNameES>Bajo</GenusNameES>
    <GenusNameJA>バス</GenusNameJA>
    <GenusNameKO>베이스</GenusNameKO>
    <GenusNamePL>Basso</GenusNamePL>
    <GenusNamePT>Baixo</GenusNamePT>
    <GenusNameRU>Бас</GenusNameRU>
    <GenusNameZH>低音</GenusNameZH>
    <GenusOrder>8</GenusOrder>
  </UIC>
  <UIC>
    <GenusType>6.Strings</GenusType>
    <GenusID>11</GenusID>
    <GenusName>Violas da braccio</GenusName>
    <GenusNameDE>Viole da braccio</GenusNameDE>
    <GenusNameFR>Viole da braccio</GenusNameFR>
    <GenusNameIT>Viole da braccio</GenusNameIT>
    <GenusNameES>Viola de brazo</GenusNameES>
    <GenusNameJA>ヴィオラ・ダ・ブラッチョ</GenusNameJA>
    <GenusNameKO>비올라 다 브라치오</GenusNameKO>
    <GenusNamePL>Violas da braccio</GenusNamePL>
    <GenusNamePT>Violas da braccio</GenusNamePT>
    <GenusNameRU>Виолы да браччо</GenusNameRU>
    <GenusNameZH>古提琴</GenusNameZH>
    <GenusOrder>9</GenusOrder>
  </UIC>
  <UIC>
    <GenusType>6.Strings</GenusType>
    <GenusID>6</GenusID>
    <GenusName>Viola d'amores</GenusName>
    <GenusNameDE>Viole d'amore</GenusNameDE>
    <GenusNameFR>Viole d'amour</GenusNameFR>
    <GenusNameIT>Viola d'amore</GenusNameIT>
    <GenusNameES>Viola de amor</GenusNameES>
    <GenusNameJA>ヴィオラ・ダモーレ</GenusNameJA>
    <GenusNameKO>비올라 다모레</GenusNameKO>
    <GenusNamePL>Viola d'amore</GenusNamePL>
    <GenusNamePT>Violas de amor</GenusNamePT>
    <GenusNameRU>Виоль д’амур</GenusNameRU>
    <GenusNameZH>古中提琴</GenusNameZH>
    <GenusOrder>12</GenusOrder>
  </UIC>
  <UIC>
    <GenusType>6.Strings</GenusType>
    <GenusID>5</GenusID>
    <GenusName>Viols</GenusName>
    <GenusNameDE>Viole da gamba</GenusNameDE>
    <GenusNameFR>Violes de gambe</GenusNameFR>
    <GenusNameIT>Viola da gamba</GenusNameIT>
    <GenusNameES>Viola de gamba</GenusNameES>
    <GenusNameJA>ヴィオラ・ダ・ガンバ</GenusNameJA>
    <GenusNameKO>비올라 다 감바</GenusNameKO>
    <GenusNamePL>Viole</GenusNamePL>
    <GenusNamePT>Violas da gamba</GenusNamePT>
    <GenusNameRU>Виолы да гамба</GenusNameRU>
    <GenusNameZH>古大提琴</GenusNameZH>
    <GenusOrder>15</GenusOrder>
  </UIC>
  <UIC>
    <GenusType>6.Strings</GenusType>
    <GenusID>10</GenusID>
    <GenusName>Ancient Strings</GenusName>
    <GenusNameDE>Ethnische Streicher</GenusNameDE>
    <GenusNameFR>Cordes antique</GenusNameFR>
    <GenusNameIT>Corde antiche</GenusNameIT>
    <GenusNameES>Cuerdas antiguas</GenusNameES>
    <GenusNameJA>弦楽古楽器</GenusNameJA>
    <GenusNameKO>고대현악기</GenusNameKO>
    <GenusNamePL>Ancient Strings</GenusNamePL>
    <GenusNamePT>Cordas antigas</GenusNamePT>
    <GenusNameRU>Старинные струнные</GenusNameRU>
    <GenusNameZH>古代弦乐器</GenusNameZH>
    <GenusOrder>16</GenusOrder>
  </UIC>
  <UIC>
    <GenusType>6.Strings</GenusType>
    <GenusID>8</GenusID>
    <GenusName>Non-Western Strings</GenusName>
    <GenusNameDE>Ethnische Streichinstrumente</GenusNameDE>
    <GenusNameFR>Cordes ethniques</GenusNameFR>
    <GenusNameIT>Archi etnici</GenusNameIT>
    <GenusNameES>Cuerdas étnicas</GenusNameES>
    <GenusNameJA>Non-Western Strings</GenusNameJA>
    <GenusNameKO>Non-Western Strings</GenusNameKO>
    <GenusNamePL>Etniczne smyczki</GenusNamePL>
    <GenusNamePT>Cordas étnicas</GenusNamePT>
    <GenusNameRU>Non-Western Strings</GenusNameRU>
    <GenusNameZH>Non-Western Strings</GenusNameZH>
    <GenusOrder>18</GenusOrder>
  </UIC>
</result>